{"request_hash":"request:anime:2379c2e551b8759e8dd4fb66732d5aa920ff6af0","request_cached":false,"request_cache_expiry":86400,"recommendations":[{"mal_id":11757,"url":"https:\/\/myanimelist.net\/anime\/11757\/Sword_Art_Online","image_url":"https:\/\/cdn.myanimelist.net\/images\/anime\/11\/39717.jpg?s=5908e8051487fb8468d5fca779f8f00d","recommendation_url":"https:\/\/myanimelist.net\/recommendations\/anime\/11757-11759","title":"Sword Art Online","recommendation_count":123},{"mal_id":10163,"url":"https:\/\/myanimelist.net\/anime\/10163\/C__The_Money_of_Soul_and_Possibility_Control","image_url":"https:\/\/cdn.myanimelist.net\/images\/anime\/5\/50551.jpg?s=c39dc8ff8a6693205b754844ad9be34a","recommendation_url":"https:\/\/myanimelist.net\/recommendations\/anime\/10163-11759","title":"C: The Money of Soul and Possibility Control","recommendation_count":13},{"mal_id":10793,"url":"https:\/\/myanimelist.net\/anime\/10793\/Guilty_Crown","image_url":"https:\/\/cdn.myanimelist.net\/images\/anime\/8\/33713.jpg?s=9dd379440569c978f0fddcf0e764c134","recommendation_url":"https:\/\/myanimelist.net\/recommendations\/anime\/10793-11759","title":"Guilty Crown","recommendation_count":11},{"mal_id":17265,"url":"https:\/\/myanimelist.net\/anime\/17265\/Log_Horizon","image_url":"https:\/\/cdn.myanimelist.net\/images\/anime\/5\/84004.jpg?s=73d4b44ed253ca5c865ef6e026cec99f","recommendation_url":"https:\/\/myanimelist.net\/recommendations\/anime\/11759-17265","title":"Log Horizon","recommendation_count":10},{"mal_id":19815,"url":"https:\/\/myanimelist.net\/anime\/19815\/No_Game_No_Life","image_url":"https:\/\/cdn.myanimelist.net\/images\/anime\/1074\/111944.jpg?s=3d63ffec8cd2a7f1e00e8dc15ef534f5","recommendation_url":"https:\/\/myanimelist.net\/recommendations\/anime\/11759-19815","title":"No Game No Life","recommendation_count":8},{"mal_id":14345,"url":"https:\/\/myanimelist.net\/anime\/14345\/Btooom","image_url":"https:\/\/cdn.myanimelist.net\/images\/anime\/4\/40977.jpg?s=7c079c4d9dc473c00a08bf6d83fe2578","recommendation_url":"https:\/\/myanimelist.net\/recommendations\/anime\/11759-14345","title":"Btooom!","recommendation_count":6},{"mal_id":6347,"url":"https:\/\/myanimelist.net\/anime\/6347\/Baka_to_Test_to_Shoukanjuu","image_url":"https:\/\/cdn.myanimelist.net\/images\/anime\/3\/50389.jpg?s=bb898c33476da7c587e8ec82afecee57","recommendation_url":"https:\/\/myanimelist.net\/recommendations\/anime\/6347-11759","title":"Baka to Test to Shoukanjuu","recommendation_count":5},{"mal_id":48,"url":"https:\/\/myanimelist.net\/anime\/48\/hack__Sign","image_url":"https:\/\/cdn.myanimelist.net\/images\/anime\/1443\/94665.jpg?s=6cb0213fea5c5edb1520ee2f542df6c3","recommendation_url":"https:\/\/myanimelist.net\/recommendations\/anime\/48-11759","title":".hack\/\/Sign","recommendation_count":5},{"mal_id":22273,"url":"https:\/\/myanimelist.net\/anime\/22273\/Selector_Infected_WIXOSS","image_url":"https:\/\/cdn.myanimelist.net\/images\/anime\/13\/70147.jpg?s=64853221c2c20d3f276e9a9b5b9cd229","recommendation_url":"https:\/\/myanimelist.net\/recommendations\/anime\/11759-22273","title":"Selector Infected WIXOSS","recommendation_count":5},{"mal_id":857,"url":"https:\/\/myanimelist.net\/anime\/857\/Air_Gear","image_url":"https:\/\/cdn.myanimelist.net\/images\/anime\/11\/18227.jpg?s=02721d59b37420549d6ab16b82cabb09","recommendation_url":"https:\/\/myanimelist.net\/recommendations\/anime\/857-11759","title":"Air Gear","recommendation_count":4},{"mal_id":11285,"url":"https:\/\/myanimelist.net\/anime\/11285\/Black\u2605Rock_Shooter_TV","image_url":"https:\/\/cdn.myanimelist.net\/images\/anime\/5\/53909.jpg?s=748577470c073b8819dc2810d9146411","recommendation_url":"https:\/\/myanimelist.net\/recommendations\/anime\/11285-11759","title":"Black\u2605Rock Shooter (TV)","recommendation_count":3},{"mal_id":14765,"url":"https:\/\/myanimelist.net\/anime\/14765\/Ixion_Saga_DT","image_url":"https:\/\/cdn.myanimelist.net\/images\/anime\/8\/42863.jpg?s=5d0b6907b1b4f703c2f8739bce7bcc94","recommendation_url":"https:\/\/myanimelist.net\/recommendations\/anime\/11759-14765","title":"Ixion Saga DT","recommendation_count":3},{"mal_id":10620,"url":"https:\/\/myanimelist.net\/anime\/10620\/Mirai_Nikki_TV","image_url":"https:\/\/cdn.myanimelist.net\/images\/anime\/13\/33465.jpg?s=47381246925211d3873b932cba7b2703","recommendation_url":"https:\/\/myanimelist.net\/recommendations\/anime\/10620-11759","title":"Mirai Nikki (TV)","recommendation_count":3},{"mal_id":1132,"url":"https:\/\/myanimelist.net\/anime\/1132\/Digimon_Frontier","image_url":"https:\/\/cdn.myanimelist.net\/images\/anime\/3\/31591.jpg?s=77cfa08ff21b581bad153cbfa7679074","recommendation_url":"https:\/\/myanimelist.net\/recommendations\/anime\/1132-11759","title":"Digimon Frontier","recommendation_count":3},{"mal_id":9332,"url":"https:\/\/myanimelist.net\/anime\/9332\/hack__Quantum","image_url":"https:\/\/cdn.myanimelist.net\/images\/anime\/5\/28371.jpg?s=1e6c9716a984c9d337972097bcccb057","recommendation_url":"https:\/\/myanimelist.net\/recommendations\/anime\/9332-11759","title":".hack\/\/Quantum","recommendation_count":3},{"mal_id":17247,"url":"https:\/\/myanimelist.net\/anime\/17247\/Machine-Doll_wa_Kizutsukanai","image_url":"https:\/\/cdn.myanimelist.net\/images\/anime\/4\/56141.jpg?s=b870661c6b331c201980d1e58cd30c6c","recommendation_url":"https:\/\/myanimelist.net\/recommendations\/anime\/11759-17247","title":"Machine-Doll wa Kizutsukanai","recommendation_count":3},{"mal_id":1710,"url":"https:\/\/myanimelist.net\/anime\/1710\/RockmanEXE","image_url":"https:\/\/cdn.myanimelist.net\/images\/anime\/2\/26575.jpg?s=89d9657dca3182ff7bb8421984a54b47","recommendation_url":"https:\/\/myanimelist.net\/recommendations\/anime\/1710-11759","title":"Rockman.EXE","recommendation_count":2},{"mal_id":14467,"url":"https:\/\/myanimelist.net\/anime\/14467\/K","image_url":"https:\/\/cdn.myanimelist.net\/images\/anime\/3\/47607.jpg?s=e96705771392afe8d0b12140d4ede7af","recommendation_url":"https:\/\/myanimelist.net\/recommendations\/anime\/11759-14467","title":"K","recommendation_count":2},{"mal_id":11617,"url":"https:\/\/myanimelist.net\/anime\/11617\/High_School_DxD","image_url":"https:\/\/cdn.myanimelist.net\/images\/anime\/1331\/111940.jpg?s=ff42c65c550aa02f8f55ffb22c6a00ce","recommendation_url":"https:\/\/myanimelist.net\/recommendations\/anime\/11617-11759","title":"High School DxD","recommendation_count":2},{"mal_id":874,"url":"https:\/\/myanimelist.net\/anime\/874\/Digimon_Tamers","image_url":"https:\/\/cdn.myanimelist.net\/images\/anime\/7\/73696.jpg?s=afce10f0c98f5c88096d083c977d83fc","recommendation_url":"https:\/\/myanimelist.net\/recommendations\/anime\/874-11759","title":"Digimon Tamers","recommendation_count":2},{"mal_id":2001,"url":"https:\/\/myanimelist.net\/anime\/2001\/Tengen_Toppa_Gurren_Lagann","image_url":"https:\/\/cdn.myanimelist.net\/images\/anime\/4\/5123.jpg?s=15bb64e0c8b13acfa5d0761308b66f59","recommendation_url":"https:\/\/myanimelist.net\/recommendations\/anime\/2001-11759","title":"Tengen Toppa Gurren Lagann","recommendation_count":2},{"mal_id":3653,"url":"https:\/\/myanimelist.net\/anime\/3653\/Kurogane_no_Linebarrels","image_url":"https:\/\/cdn.myanimelist.net\/images\/anime\/2\/50375.jpg?s=1dd2cf0c1709dad82ebcf292e1208936","recommendation_url":"https:\/\/myanimelist.net\/recommendations\/anime\/3653-11759","title":"Kurogane no Linebarrels","recommendation_count":2},{"mal_id":552,"url":"https:\/\/myanimelist.net\/anime\/552\/Digimon_Adventure","image_url":"https:\/\/cdn.myanimelist.net\/images\/anime\/10\/11070.jpg?s=b47536a4881415d0e905699733016194","recommendation_url":"https:\/\/myanimelist.net\/recommendations\/anime\/552-11759","title":"Digimon Adventure","recommendation_count":2},{"mal_id":4654,"url":"https:\/\/myanimelist.net\/anime\/4654\/Toaru_Majutsu_no_Index","image_url":"https:\/\/cdn.myanimelist.net\/images\/anime\/2\/75533.jpg?s=dfc8b107dd7ff99cd0f1f2994f09cea9","recommendation_url":"https:\/\/myanimelist.net\/recommendations\/anime\/4654-11759","title":"Toaru Majutsu no Index","recommendation_count":2},{"mal_id":16512,"url":"https:\/\/myanimelist.net\/anime\/16512\/Devil_Survivor_2_The_Animation","image_url":"https:\/\/cdn.myanimelist.net\/images\/anime\/11\/47191.jpg?s=1c3f377ef173bee43826258cac57d16e","recommendation_url":"https:\/\/myanimelist.net\/recommendations\/anime\/11759-16512","title":"Devil Survivor 2 The Animation","recommendation_count":2},{"mal_id":10588,"url":"https:\/\/myanimelist.net\/anime\/10588\/Persona_4_the_Animation","image_url":"https:\/\/cdn.myanimelist.net\/images\/anime\/4\/29107.jpg?s=21bf252fdd71f312a8c87871163e3f88","recommendation_url":"https:\/\/myanimelist.net\/recommendations\/anime\/10588-11759","title":"Persona 4 the Animation","recommendation_count":2},{"mal_id":15583,"url":"https:\/\/myanimelist.net\/anime\/15583\/Date_A_Live","image_url":"https:\/\/cdn.myanimelist.net\/images\/anime\/13\/44844.jpg?s=c1da4993c7a0a09b0e104ecbd8065deb","recommendation_url":"https:\/\/myanimelist.net\/recommendations\/anime\/11759-15583","title":"Date A Live","recommendation_count":2},{"mal_id":38656,"url":"https:\/\/myanimelist.net\/anime\/38656\/Darwins_Game","image_url":"https:\/\/cdn.myanimelist.net\/images\/anime\/1016\/107222.jpg?s=19c73f7fc5737c9f225c77bb99ce3906","recommendation_url":"https:\/\/myanimelist.net\/recommendations\/anime\/11759-38656","title":"Darwin's Game","recommendation_count":2},{"mal_id":5681,"url":"https:\/\/myanimelist.net\/anime\/5681\/Summer_Wars","image_url":"https:\/\/cdn.myanimelist.net\/images\/anime\/10\/15796.jpg?s=0b9114a4f1e20d7dd08fda2c64483ef9","recommendation_url":"https:\/\/myanimelist.net\/recommendations\/anime\/5681-11759","title":"Summer Wars","recommendation_count":2},{"mal_id":1682,"url":"https:\/\/myanimelist.net\/anime\/1682\/Baldr_Force_Exe_Resolution","image_url":"https:\/\/cdn.myanimelist.net\/images\/anime\/3\/76295.jpg?s=d19d0d736ace0c8e28231596837d3235","recommendation_url":"https:\/\/myanimelist.net\/recommendations\/anime\/1682-11759","title":"Baldr Force Exe Resolution","recommendation_count":2},{"mal_id":1575,"url":"https:\/\/myanimelist.net\/anime\/1575\/Code_Geass__Hangyaku_no_Lelouch","image_url":"https:\/\/cdn.myanimelist.net\/images\/anime\/5\/50331.jpg?s=afd09d7e5d76283418a1a22e7c122ca9","recommendation_url":"https:\/\/myanimelist.net\/recommendations\/anime\/1575-11759","title":"Code Geass: Hangyaku no Lelouch","recommendation_count":2},{"mal_id":2112,"url":"https:\/\/myanimelist.net\/anime\/2112\/Over_Drive","image_url":"https:\/\/cdn.myanimelist.net\/images\/anime\/3\/89534.jpg?s=d978588dd3494dff6c9eb1511ed0f335","recommendation_url":"https:\/\/myanimelist.net\/recommendations\/anime\/2112-11759","title":"Over Drive","recommendation_count":1},{"mal_id":29803,"url":"https:\/\/myanimelist.net\/anime\/29803\/Overlord","image_url":"https:\/\/cdn.myanimelist.net\/images\/anime\/7\/88019.jpg?s=79b1142c4818577b9925017b0240131a","recommendation_url":"https:\/\/myanimelist.net\/recommendations\/anime\/11759-29803","title":"Overlord","recommendation_count":1},{"mal_id":4981,"url":"https:\/\/myanimelist.net\/anime\/4981\/Casshern_Sins","image_url":"https:\/\/cdn.myanimelist.net\/images\/anime\/8\/23336.jpg?s=fb3c10e711f2633c82f8a8b660251542","recommendation_url":"https:\/\/myanimelist.net\/recommendations\/anime\/4981-11759","title":"Casshern Sins","recommendation_count":1},{"mal_id":384,"url":"https:\/\/myanimelist.net\/anime\/384\/Gantz","image_url":"https:\/\/cdn.myanimelist.net\/images\/anime\/13\/5998.jpg?s=3729cee1ddb0a337b9586b9897b77495","recommendation_url":"https:\/\/myanimelist.net\/recommendations\/anime\/384-11759","title":"Gantz","recommendation_count":1},{"mal_id":1210,"url":"https:\/\/myanimelist.net\/anime\/1210\/NHK_ni_Youkoso","image_url":"https:\/\/cdn.myanimelist.net\/images\/anime\/3\/52675.jpg?s=e0121ee07b2b86ae6fde9c7f35278a6b","recommendation_url":"https:\/\/myanimelist.net\/recommendations\/anime\/1210-11759","title":"NHK ni Youkoso!","recommendation_count":1},{"mal_id":6880,"url":"https:\/\/myanimelist.net\/anime\/6880\/Deadman_Wonderland","image_url":"https:\/\/cdn.myanimelist.net\/images\/anime\/9\/75299.jpg?s=f63ee6e23071ae4492e9d8c9c570ebbc","recommendation_url":"https:\/\/myanimelist.net\/recommendations\/anime\/6880-11759","title":"Deadman Wonderland","recommendation_count":1},{"mal_id":11933,"url":"https:\/\/myanimelist.net\/anime\/11933\/Oda_Nobuna_no_Yabou","image_url":"https:\/\/cdn.myanimelist.net\/images\/anime\/11\/39249.jpg?s=33d9505a271342ca4136d2bd687aeebc","recommendation_url":"https:\/\/myanimelist.net\/recommendations\/anime\/11759-11933","title":"Oda Nobuna no Yabou","recommendation_count":1},{"mal_id":24011,"url":"https:\/\/myanimelist.net\/anime\/24011\/Lance_N_Masques","image_url":"https:\/\/cdn.myanimelist.net\/images\/anime\/13\/76576.jpg?s=774dccab82bcf21db1d6849f8f6c93b9","recommendation_url":"https:\/\/myanimelist.net\/recommendations\/anime\/11759-24011","title":"Lance N' Masques","recommendation_count":1},{"mal_id":23273,"url":"https:\/\/myanimelist.net\/anime\/23273\/Shigatsu_wa_Kimi_no_Uso","image_url":"https:\/\/cdn.myanimelist.net\/images\/anime\/3\/67177.jpg?s=bc267f764bffe825e1e8d60f7185a2e9","recommendation_url":"https:\/\/myanimelist.net\/recommendations\/anime\/11759-23273","title":"Shigatsu wa Kimi no Uso","recommendation_count":1},{"mal_id":5734,"url":"https:\/\/myanimelist.net\/anime\/5734\/Tayutama__Kiss_on_My_Deity","image_url":"https:\/\/cdn.myanimelist.net\/images\/anime\/2\/11972.jpg?s=00163cbe177222dc67b1eec3392afe46","recommendation_url":"https:\/\/myanimelist.net\/recommendations\/anime\/5734-11759","title":"Tayutama: Kiss on My Deity","recommendation_count":1},{"mal_id":36266,"url":"https:\/\/myanimelist.net\/anime\/36266\/Mahou_Shoujo_Site","image_url":"https:\/\/cdn.myanimelist.net\/images\/anime\/1720\/95064.jpg?s=571fd140e4695a0f49fd2513621fb562","recommendation_url":"https:\/\/myanimelist.net\/recommendations\/anime\/11759-36266","title":"Mahou Shoujo Site","recommendation_count":1},{"mal_id":28121,"url":"https:\/\/myanimelist.net\/anime\/28121\/Dungeon_ni_Deai_wo_Motomeru_no_wa_Machigatteiru_Darou_ka","image_url":"https:\/\/cdn.myanimelist.net\/images\/anime\/2\/70187.jpg?s=91227c20276828bcb0e6c5b4017c0732","recommendation_url":"https:\/\/myanimelist.net\/recommendations\/anime\/11759-28121","title":"Dungeon ni Deai wo Motomeru no wa Machigatteiru Darou ka","recommendation_count":1},{"mal_id":6023,"url":"https:\/\/myanimelist.net\/anime\/6023\/Nogizaka_Haruka_no_Himitsu__Purezza","image_url":"https:\/\/cdn.myanimelist.net\/images\/anime\/10\/74013.jpg?s=69182f51753d2d654aa9234684afde49","recommendation_url":"https:\/\/myanimelist.net\/recommendations\/anime\/6023-11759","title":"Nogizaka Haruka no Himitsu: Purezza","recommendation_count":1},{"mal_id":21881,"url":"https:\/\/myanimelist.net\/anime\/21881\/Sword_Art_Online_II","image_url":"https:\/\/cdn.myanimelist.net\/images\/anime\/11\/65185.jpg?s=c64b7a5e12025712ff5a442fcc67bcef","recommendation_url":"https:\/\/myanimelist.net\/recommendations\/anime\/11759-21881","title":"Sword Art Online II","recommendation_count":1},{"mal_id":9367,"url":"https:\/\/myanimelist.net\/anime\/9367\/Freezing","image_url":"https:\/\/cdn.myanimelist.net\/images\/anime\/10\/28535.jpg?s=8c31ff6cf0f2275a05ede3594eed587b","recommendation_url":"https:\/\/myanimelist.net\/recommendations\/anime\/9367-11759","title":"Freezing","recommendation_count":1},{"mal_id":11751,"url":"https:\/\/myanimelist.net\/anime\/11751\/Senki_Zesshou_Symphogear","image_url":"https:\/\/cdn.myanimelist.net\/images\/anime\/11\/75580.jpg?s=33e8612b01627946bd63b3734d71e3ca","recommendation_url":"https:\/\/myanimelist.net\/recommendations\/anime\/11751-11759","title":"Senki Zesshou Symphogear","recommendation_count":1},{"mal_id":11375,"url":"https:\/\/myanimelist.net\/anime\/11375\/hack__The_Movie__Sekai_no_Mukou_ni","image_url":"https:\/\/cdn.myanimelist.net\/images\/anime\/2\/35633.jpg?s=1786faaf28951c31d9df998658c24e3e","recommendation_url":"https:\/\/myanimelist.net\/recommendations\/anime\/11375-11759","title":".hack\/\/The Movie: Sekai no Mukou ni","recommendation_count":1},{"mal_id":6547,"url":"https:\/\/myanimelist.net\/anime\/6547\/Angel_Beats","image_url":"https:\/\/cdn.myanimelist.net\/images\/anime\/1244\/111115.jpg?s=14607c2ea405539df501e29595daa582","recommendation_url":"https:\/\/myanimelist.net\/recommendations\/anime\/6547-11759","title":"Angel Beats!","recommendation_count":1},{"mal_id":8934,"url":"https:\/\/myanimelist.net\/anime\/8934\/Star_Driver__Kagayaki_no_Takuto","image_url":"https:\/\/cdn.myanimelist.net\/images\/anime\/4\/25953.jpg?s=318acdf72b1a3e66ecd647d62598436b","recommendation_url":"https:\/\/myanimelist.net\/recommendations\/anime\/8934-11759","title":"Star Driver: Kagayaki no Takuto","recommendation_count":1},{"mal_id":9989,"url":"https:\/\/myanimelist.net\/anime\/9989\/Ano_Hi_Mita_Hana_no_Namae_wo_Bokutachi_wa_Mada_Shiranai","image_url":"https:\/\/cdn.myanimelist.net\/images\/anime\/5\/79697.jpg?s=c664a137ce3f854a2343cf39921ae579","recommendation_url":"https:\/\/myanimelist.net\/recommendations\/anime\/9989-11759","title":"Ano Hi Mita Hana no Namae wo Bokutachi wa Mada Shiranai.","recommendation_count":1},{"mal_id":3561,"url":"https:\/\/myanimelist.net\/anime\/3561\/Dennou_Boukenki_Webdiver","image_url":"https:\/\/cdn.myanimelist.net\/images\/anime\/12\/5989.jpg?s=574f4b81a5b85b5ded0099269b219c54","recommendation_url":"https:\/\/myanimelist.net\/recommendations\/anime\/3561-11759","title":"Dennou Boukenki Webdiver","recommendation_count":1},{"mal_id":5958,"url":"https:\/\/myanimelist.net\/anime\/5958\/Sora_no_Otoshimono","image_url":"https:\/\/cdn.myanimelist.net\/images\/anime\/5\/50307.jpg?s=b488dfd79bc7f2da7501cdfa8cd8d319","recommendation_url":"https:\/\/myanimelist.net\/recommendations\/anime\/5958-11759","title":"Sora no Otoshimono","recommendation_count":1},{"mal_id":1792,"url":"https:\/\/myanimelist.net\/anime\/1792\/Overman_King_Gainer","image_url":"https:\/\/cdn.myanimelist.net\/images\/anime\/5\/44135.jpg?s=cf9eeef1170d23e2ad3aab5708a08e15","recommendation_url":"https:\/\/myanimelist.net\/recommendations\/anime\/1792-11759","title":"Overman King Gainer","recommendation_count":1},{"mal_id":878,"url":"https:\/\/myanimelist.net\/anime\/878\/Zegapain","image_url":"https:\/\/cdn.myanimelist.net\/images\/anime\/6\/76949.jpg?s=9aaaa16c73c98667234716b0b53f834e","recommendation_url":"https:\/\/myanimelist.net\/recommendations\/anime\/878-11759","title":"Zegapain","recommendation_count":1},{"mal_id":298,"url":"https:\/\/myanimelist.net\/anime\/298\/hack__Tasogare_no_Udewa_Densetsu","image_url":"https:\/\/cdn.myanimelist.net\/images\/anime\/4\/78321.jpg?s=9dc5fdbef66fe340d18b50b9b04b979d","recommendation_url":"https:\/\/myanimelist.net\/recommendations\/anime\/298-11759","title":".hack\/\/Tasogare no Udewa Densetsu","recommendation_count":1},{"mal_id":21,"url":"https:\/\/myanimelist.net\/anime\/21\/One_Piece","image_url":"https:\/\/cdn.myanimelist.net\/images\/anime\/6\/73245.jpg?s=f792b8c9e28534ae455d06b15e686a14","recommendation_url":"https:\/\/myanimelist.net\/recommendations\/anime\/21-11759","title":"One Piece","recommendation_count":1},{"mal_id":22199,"url":"https:\/\/myanimelist.net\/anime\/22199\/Akame_ga_Kill","image_url":"https:\/\/cdn.myanimelist.net\/images\/anime\/1429\/95946.jpg?s=54a1d4bcd881957ce164297f36df5a72","recommendation_url":"https:\/\/myanimelist.net\/recommendations\/anime\/11759-22199","title":"Akame ga Kill!","recommendation_count":1},{"mal_id":13175,"url":"https:\/\/myanimelist.net\/anime\/13175\/Shiranpuri_Movie","image_url":"https:\/\/cdn.myanimelist.net\/images\/anime\/4\/50407.jpg?s=905e5b701a2d91066364f1c6f4377da5","recommendation_url":"https:\/\/myanimelist.net\/recommendations\/anime\/11759-13175","title":"Shiranpuri (Movie)","recommendation_count":1},{"mal_id":9981,"url":"https:\/\/myanimelist.net\/anime\/9981\/Phi_Brain__Kami_no_Puzzle","image_url":"https:\/\/cdn.myanimelist.net\/images\/anime\/12\/34045.jpg?s=b0f4d0976fc27292784b4dbe299011d2","recommendation_url":"https:\/\/myanimelist.net\/recommendations\/anime\/9981-11759","title":"Phi Brain: Kami no Puzzle","recommendation_count":1},{"mal_id":10463,"url":"https:\/\/myanimelist.net\/anime\/10463\/Exper_Zenon","image_url":"https:\/\/cdn.myanimelist.net\/images\/anime\/1509\/105899.jpg?s=8ea56a109a8048ea23866b17edfe3a35","recommendation_url":"https:\/\/myanimelist.net\/recommendations\/anime\/10463-11759","title":"Exper Zenon","recommendation_count":1},{"mal_id":3359,"url":"https:\/\/myanimelist.net\/anime\/3359\/Amatsuki","image_url":"https:\/\/cdn.myanimelist.net\/images\/anime\/12\/75555.jpg?s=832c4ea91f8ff3dc7c336efa82674e57","recommendation_url":"https:\/\/myanimelist.net\/recommendations\/anime\/3359-11759","title":"Amatsuki","recommendation_count":1},{"mal_id":6408,"url":"https:\/\/myanimelist.net\/anime\/6408\/Bungaku_Shoujo_Movie","image_url":"https:\/\/cdn.myanimelist.net\/images\/anime\/8\/81162.jpg?s=dc005b3dc3f13e250b40f01b5a3baec0","recommendation_url":"https:\/\/myanimelist.net\/recommendations\/anime\/6408-11759","title":"\"Bungaku Shoujo\" Movie","recommendation_count":1},{"mal_id":9314,"url":"https:\/\/myanimelist.net\/anime\/9314\/Fractale","image_url":"https:\/\/cdn.myanimelist.net\/images\/anime\/2\/28197.jpg?s=6f1d706f611da086dcc6231ccf14ec6d","recommendation_url":"https:\/\/myanimelist.net\/recommendations\/anime\/9314-11759","title":"Fractale","recommendation_count":1},{"mal_id":5342,"url":"https:\/\/myanimelist.net\/anime\/5342\/Asura_Cryin","image_url":"https:\/\/cdn.myanimelist.net\/images\/anime\/7\/17071.jpg?s=c6f184711b233e4e10502b5f553e6b32","recommendation_url":"https:\/\/myanimelist.net\/recommendations\/anime\/5342-11759","title":"Asura Cryin'","recommendation_count":1},{"mal_id":4975,"url":"https:\/\/myanimelist.net\/anime\/4975\/Ch\u00e4oS_HEAd","image_url":"https:\/\/cdn.myanimelist.net\/images\/anime\/13\/15443.jpg?s=0e8bc16d923a1e01645906820e780391","recommendation_url":"https:\/\/myanimelist.net\/recommendations\/anime\/4975-11759","title":"Ch\u00e4oS;HEAd","recommendation_count":1},{"mal_id":2966,"url":"https:\/\/myanimelist.net\/anime\/2966\/Ookami_to_Koushinryou","image_url":"https:\/\/cdn.myanimelist.net\/images\/anime\/5\/59401.jpg?s=1c81971daf350f8e99fe00fe3bbd0f95","recommendation_url":"https:\/\/myanimelist.net\/recommendations\/anime\/2966-11759","title":"Ookami to Koushinryou","recommendation_count":1},{"mal_id":22547,"url":"https:\/\/myanimelist.net\/anime\/22547\/Blade___Soul","image_url":"https:\/\/cdn.myanimelist.net\/images\/anime\/11\/61885.jpg?s=456caf1bd10dbb677d674033203b4434","recommendation_url":"https:\/\/myanimelist.net\/recommendations\/anime\/11759-22547","title":"Blade & Soul","recommendation_count":1},{"mal_id":8525,"url":"https:\/\/myanimelist.net\/anime\/8525\/Kami_nomi_zo_Shiru_Sekai","image_url":"https:\/\/cdn.myanimelist.net\/images\/anime\/2\/43361.jpg?s=529d5cf9682899d828bca18eb8088c72","recommendation_url":"https:\/\/myanimelist.net\/recommendations\/anime\/8525-11759","title":"Kami nomi zo Shiru Sekai","recommendation_count":1},{"mal_id":9936,"url":"https:\/\/myanimelist.net\/anime\/9936\/Maken-Ki","image_url":"https:\/\/cdn.myanimelist.net\/images\/anime\/2\/75234.jpg?s=4493685100b3149130a1d050695283c6","recommendation_url":"https:\/\/myanimelist.net\/recommendations\/anime\/9936-11759","title":"Maken-Ki!","recommendation_count":1},{"mal_id":18229,"url":"https:\/\/myanimelist.net\/anime\/18229\/Gatchaman_Crowds","image_url":"https:\/\/cdn.myanimelist.net\/images\/anime\/7\/52471.jpg?s=bda04521318afa123209b2eaebb72cef","recommendation_url":"https:\/\/myanimelist.net\/recommendations\/anime\/11759-18229","title":"Gatchaman Crowds","recommendation_count":1},{"mal_id":14833,"url":"https:\/\/myanimelist.net\/anime\/14833\/Maoyuu_Maou_Yuusha","image_url":"https:\/\/cdn.myanimelist.net\/images\/anime\/4\/46041.jpg?s=b25220a6f1abb819423ee21c7d344cbc","recommendation_url":"https:\/\/myanimelist.net\/recommendations\/anime\/11759-14833","title":"Maoyuu Maou Yuusha","recommendation_count":1},{"mal_id":6682,"url":"https:\/\/myanimelist.net\/anime\/6682\/11eyes","image_url":"https:\/\/cdn.myanimelist.net\/images\/anime\/6\/73520.jpg?s=a0e5054dc05bdb4de1e15ffe7f71bbcd","recommendation_url":"https:\/\/myanimelist.net\/recommendations\/anime\/6682-11759","title":"11eyes","recommendation_count":1},{"mal_id":2164,"url":"https:\/\/myanimelist.net\/anime\/2164\/Dennou_Coil","image_url":"https:\/\/cdn.myanimelist.net\/images\/anime\/5\/12844.jpg?s=613f2f1c8971c8ae279ec47a57d03e90","recommendation_url":"https:\/\/myanimelist.net\/recommendations\/anime\/2164-11759","title":"Dennou Coil","recommendation_count":1},{"mal_id":1835,"url":"https:\/\/myanimelist.net\/anime\/1835\/Ryuusei_no_Rockman","image_url":"https:\/\/cdn.myanimelist.net\/images\/anime\/3\/26600.jpg?s=24b56b556a9a129df6cd0a054f6e4809","recommendation_url":"https:\/\/myanimelist.net\/recommendations\/anime\/1835-11759","title":"Ryuusei no Rockman","recommendation_count":1},{"mal_id":18247,"url":"https:\/\/myanimelist.net\/anime\/18247\/IS__Infinite_Stratos_2","image_url":"https:\/\/cdn.myanimelist.net\/images\/anime\/12\/49359.jpg?s=63a708ef8e2bd70c49bdffcfbc57f1b0","recommendation_url":"https:\/\/myanimelist.net\/recommendations\/anime\/11759-18247","title":"IS: Infinite Stratos 2","recommendation_count":1},{"mal_id":356,"url":"https:\/\/myanimelist.net\/anime\/356\/Fate_stay_night","image_url":"https:\/\/cdn.myanimelist.net\/images\/anime\/4\/30327.jpg?s=83d26b95fcc7fc4297332ebc4497e91a","recommendation_url":"https:\/\/myanimelist.net\/recommendations\/anime\/356-11759","title":"Fate\/stay night","recommendation_count":1}]}