{"request_hash":"request:anime:bceab275fea5deeabd85492ebd63765a89a1f453","request_cached":false,"request_cache_expiry":86400,"recommendations":[{"mal_id":918,"url":"https:\/\/myanimelist.net\/anime\/918\/Gintama","image_url":"https:\/\/cdn.myanimelist.net\/images\/anime\/10\/73274.jpg?s=ed42453c10ba12b03b1600d02725a174","recommendation_url":"https:\/\/myanimelist.net\/recommendations\/anime\/918-13535","title":"Gintama","recommendation_count":13},{"mal_id":11785,"url":"https:\/\/myanimelist.net\/anime\/11785\/Haiyore_Nyaruko-san","image_url":"https:\/\/cdn.myanimelist.net\/images\/anime\/6\/49081.jpg?s=6f324decb780258bf84256a8ffe6651c","recommendation_url":"https:\/\/myanimelist.net\/recommendations\/anime\/11785-13535","title":"Haiyore! Nyaruko-san","recommendation_count":7},{"mal_id":2104,"url":"https:\/\/myanimelist.net\/anime\/2104\/Seto_no_Hanayome","image_url":"https:\/\/cdn.myanimelist.net\/images\/anime\/13\/58383.jpg?s=443c64d627751784a5fbe7a65c0cc9c6","recommendation_url":"https:\/\/myanimelist.net\/recommendations\/anime\/2104-13535","title":"Seto no Hanayome","recommendation_count":5},{"mal_id":11843,"url":"https:\/\/myanimelist.net\/anime\/11843\/Danshi_Koukousei_no_Nichijou","image_url":"https:\/\/cdn.myanimelist.net\/images\/anime\/3\/33257.jpg?s=d0bbef34d6992bb86a1395f1fc09fe6b","recommendation_url":"https:\/\/myanimelist.net\/recommendations\/anime\/11843-13535","title":"Danshi Koukousei no Nichijou","recommendation_count":5},{"mal_id":20709,"url":"https:\/\/myanimelist.net\/anime\/20709\/Sabage-bu","image_url":"https:\/\/cdn.myanimelist.net\/images\/anime\/13\/60207.jpg?s=ac709f6bab03b5317bba4df33ebb2a02","recommendation_url":"https:\/\/myanimelist.net\/recommendations\/anime\/13535-20709","title":"Sabage-bu!","recommendation_count":4},{"mal_id":379,"url":"https:\/\/myanimelist.net\/anime\/379\/Heppoko_Jikken_Animation_Excel\u2665Saga","image_url":"https:\/\/cdn.myanimelist.net\/images\/anime\/1728\/97423.jpg?s=92698ba080f13a6f108c2e4f3d50878c","recommendation_url":"https:\/\/myanimelist.net\/recommendations\/anime\/379-13535","title":"Heppoko Jikken Animation Excel\u2665Saga","recommendation_count":3},{"mal_id":20031,"url":"https:\/\/myanimelist.net\/anime\/20031\/D-Frag","image_url":"https:\/\/cdn.myanimelist.net\/images\/anime\/1662\/112108.jpg?s=86648fbb3b230c57529add1c38dedbae","recommendation_url":"https:\/\/myanimelist.net\/recommendations\/anime\/13535-20031","title":"D-Frag!","recommendation_count":3},{"mal_id":15809,"url":"https:\/\/myanimelist.net\/anime\/15809\/Hataraku_Maou-sama","image_url":"https:\/\/cdn.myanimelist.net\/images\/anime\/3\/50177.jpg?s=806f9709a27518b8243d0d881f5384ff","recommendation_url":"https:\/\/myanimelist.net\/recommendations\/anime\/13535-15809","title":"Hataraku Maou-sama!","recommendation_count":3},{"mal_id":9513,"url":"https:\/\/myanimelist.net\/anime\/9513\/Beelzebub","image_url":"https:\/\/cdn.myanimelist.net\/images\/anime\/3\/28013.jpg?s=33c1e4b2fc322189b6799b171e342a04","recommendation_url":"https:\/\/myanimelist.net\/recommendations\/anime\/9513-13535","title":"Beelzebub","recommendation_count":3},{"mal_id":9863,"url":"https:\/\/myanimelist.net\/anime\/9863\/SKET_Dance","image_url":"https:\/\/cdn.myanimelist.net\/images\/anime\/9\/73974.jpg?s=ad99ee6b839d45b97b47fef353bac61d","recommendation_url":"https:\/\/myanimelist.net\/recommendations\/anime\/9863-13535","title":"SKET Dance","recommendation_count":2},{"mal_id":33255,"url":"https:\/\/myanimelist.net\/anime\/33255\/Saiki_Kusuo_no_\u03a8-nan","image_url":"https:\/\/cdn.myanimelist.net\/images\/anime\/11\/80167.jpg?s=1c4f87499deea4f4dbc09805e23bf243","recommendation_url":"https:\/\/myanimelist.net\/recommendations\/anime\/13535-33255","title":"Saiki Kusuo no \u03a8-nan","recommendation_count":2},{"mal_id":23289,"url":"https:\/\/myanimelist.net\/anime\/23289\/Gekkan_Shoujo_Nozaki-kun","image_url":"https:\/\/cdn.myanimelist.net\/images\/anime\/5\/66083.jpg?s=59ab3e9362a2bbed54ae5420b27032bb","recommendation_url":"https:\/\/myanimelist.net\/recommendations\/anime\/13535-23289","title":"Gekkan Shoujo Nozaki-kun","recommendation_count":2},{"mal_id":7647,"url":"https:\/\/myanimelist.net\/anime\/7647\/Arakawa_Under_the_Bridge","image_url":"https:\/\/cdn.myanimelist.net\/images\/anime\/2\/59197.jpg?s=1f9892d79e07d372945b8f33554b17fe","recommendation_url":"https:\/\/myanimelist.net\/recommendations\/anime\/7647-13535","title":"Arakawa Under the Bridge","recommendation_count":2},{"mal_id":933,"url":"https:\/\/myanimelist.net\/anime\/933\/Dai_Mahou_Touge","image_url":"https:\/\/cdn.myanimelist.net\/images\/anime\/11\/20582.jpg?s=a47468a43b910c7e0f06c3526ceb752b","recommendation_url":"https:\/\/myanimelist.net\/recommendations\/anime\/933-13535","title":"Dai Mahou Touge","recommendation_count":2},{"mal_id":8795,"url":"https:\/\/myanimelist.net\/anime\/8795\/Panty___Stocking_with_Garterbelt","image_url":"https:\/\/cdn.myanimelist.net\/images\/anime\/12\/73643.jpg?s=c358e22c4b272a05abb835c09aa46cd7","recommendation_url":"https:\/\/myanimelist.net\/recommendations\/anime\/8795-13535","title":"Panty & Stocking with Garterbelt","recommendation_count":2},{"mal_id":32262,"url":"https:\/\/myanimelist.net\/anime\/32262\/Renai_Boukun","image_url":"https:\/\/cdn.myanimelist.net\/images\/anime\/9\/84266.jpg?s=da1b12fc916b17e2d6cc7343f4e13243","recommendation_url":"https:\/\/myanimelist.net\/recommendations\/anime\/13535-32262","title":"Renai Boukun","recommendation_count":2},{"mal_id":11633,"url":"https:\/\/myanimelist.net\/anime\/11633\/Blood_Lad","image_url":"https:\/\/cdn.myanimelist.net\/images\/anime\/11\/47677.jpg?s=6305d2a6b71738d6d7d79e59ca5418c6","recommendation_url":"https:\/\/myanimelist.net\/recommendations\/anime\/11633-13535","title":"Blood Lad","recommendation_count":2},{"mal_id":35821,"url":"https:\/\/myanimelist.net\/anime\/35821\/Chio-chan_no_Tsuugakuro","image_url":"https:\/\/cdn.myanimelist.net\/images\/anime\/1073\/95042.jpg?s=9e8d2661b06983f8db4f74fbb47e9991","recommendation_url":"https:\/\/myanimelist.net\/recommendations\/anime\/13535-35821","title":"Chio-chan no Tsuugakuro","recommendation_count":1},{"mal_id":20057,"url":"https:\/\/myanimelist.net\/anime\/20057\/Space\u2606Dandy","image_url":"https:\/\/cdn.myanimelist.net\/images\/anime\/4\/56611.jpg?s=d950260ff196f3b5287093ca30c8f03a","recommendation_url":"https:\/\/myanimelist.net\/recommendations\/anime\/13535-20057","title":"Space\u2606Dandy","recommendation_count":1},{"mal_id":6347,"url":"https:\/\/myanimelist.net\/anime\/6347\/Baka_to_Test_to_Shoukanjuu","image_url":"https:\/\/cdn.myanimelist.net\/images\/anime\/3\/50389.jpg?s=bb898c33476da7c587e8ec82afecee57","recommendation_url":"https:\/\/myanimelist.net\/recommendations\/anime\/6347-13535","title":"Baka to Test to Shoukanjuu","recommendation_count":1},{"mal_id":516,"url":"https:\/\/myanimelist.net\/anime\/516\/Keroro_Gunsou","image_url":"https:\/\/cdn.myanimelist.net\/images\/anime\/2\/21764.jpg?s=26600082b1f57f4e55499cfae20c900b","recommendation_url":"https:\/\/myanimelist.net\/recommendations\/anime\/516-13535","title":"Keroro Gunsou","recommendation_count":1},{"mal_id":1887,"url":"https:\/\/myanimelist.net\/anime\/1887\/Lucky\u2606Star","image_url":"https:\/\/cdn.myanimelist.net\/images\/anime\/1561\/115660.jpg?s=79acc51ecc77b35fe5f61096dec935c3","recommendation_url":"https:\/\/myanimelist.net\/recommendations\/anime\/1887-13535","title":"Lucky\u2606Star","recommendation_count":1},{"mal_id":3455,"url":"https:\/\/myanimelist.net\/anime\/3455\/To_LOVE-Ru","image_url":"https:\/\/cdn.myanimelist.net\/images\/anime\/13\/22544.jpg?s=c433699f1bb4e7243754703dff0bdb32","recommendation_url":"https:\/\/myanimelist.net\/recommendations\/anime\/3455-13535","title":"To LOVE-Ru","recommendation_count":1},{"mal_id":3616,"url":"https:\/\/myanimelist.net\/anime\/3616\/Kamen_no_Maid_Guy","image_url":"https:\/\/cdn.myanimelist.net\/images\/anime\/4\/77694.jpg?s=8eab147c02b1908cbc68ee69de986ca4","recommendation_url":"https:\/\/myanimelist.net\/recommendations\/anime\/3616-13535","title":"Kamen no Maid Guy","recommendation_count":1},{"mal_id":28677,"url":"https:\/\/myanimelist.net\/anime\/28677\/Yamada-kun_to_7-nin_no_Majo_TV","image_url":"https:\/\/cdn.myanimelist.net\/images\/anime\/2\/73700.jpg?s=b9b9724f07fa8831f77d7cf00aec8379","recommendation_url":"https:\/\/myanimelist.net\/recommendations\/anime\/13535-28677","title":"Yamada-kun to 7-nin no Majo (TV)","recommendation_count":1},{"mal_id":36906,"url":"https:\/\/myanimelist.net\/anime\/36906\/Jashin-chan_Dropkick","image_url":"https:\/\/cdn.myanimelist.net\/images\/anime\/1892\/93420.jpg?s=9db7ab4bec0e5f561fb605a1f1b9861b","recommendation_url":"https:\/\/myanimelist.net\/recommendations\/anime\/13535-36906","title":"Jashin-chan Dropkick","recommendation_count":1},{"mal_id":31174,"url":"https:\/\/myanimelist.net\/anime\/31174\/Osomatsu-san","image_url":"https:\/\/cdn.myanimelist.net\/images\/anime\/7\/76540.jpg?s=e2dbeb88814fcbd849d2f1616ef6a050","recommendation_url":"https:\/\/myanimelist.net\/recommendations\/anime\/13535-31174","title":"Osomatsu-san","recommendation_count":1},{"mal_id":28825,"url":"https:\/\/myanimelist.net\/anime\/28825\/Himouto_Umaru-chan","image_url":"https:\/\/cdn.myanimelist.net\/images\/anime\/12\/75086.jpg?s=3859e8b6e84fb62187f8f71e86f02484","recommendation_url":"https:\/\/myanimelist.net\/recommendations\/anime\/13535-28825","title":"Himouto! Umaru-chan","recommendation_count":1},{"mal_id":17777,"url":"https:\/\/myanimelist.net\/anime\/17777\/Saikin_Imouto_no_Yousu_ga_Chotto_Okashiinda_ga","image_url":"https:\/\/cdn.myanimelist.net\/images\/anime\/3\/56589.jpg?s=5e7abad6f80ac18268a2f849540bac48","recommendation_url":"https:\/\/myanimelist.net\/recommendations\/anime\/13535-17777","title":"Saikin, Imouto no Yousu ga Chotto Okashiinda ga.","recommendation_count":1},{"mal_id":249,"url":"https:\/\/myanimelist.net\/anime\/249\/InuYasha","image_url":"https:\/\/cdn.myanimelist.net\/images\/anime\/1589\/95329.jpg?s=8254094634e2145d86d63438c0ab9205","recommendation_url":"https:\/\/myanimelist.net\/recommendations\/anime\/249-13535","title":"InuYasha","recommendation_count":1},{"mal_id":18095,"url":"https:\/\/myanimelist.net\/anime\/18095\/Nourin","image_url":"https:\/\/cdn.myanimelist.net\/images\/anime\/6\/57563.jpg?s=b0421067500e1485d5bc825361979fb1","recommendation_url":"https:\/\/myanimelist.net\/recommendations\/anime\/13535-18095","title":"Nourin","recommendation_count":1},{"mal_id":23673,"url":"https:\/\/myanimelist.net\/anime\/23673\/Ookami_Shoujo_to_Kuro_Ouji","image_url":"https:\/\/cdn.myanimelist.net\/images\/anime\/4\/67805.jpg?s=16b232d9ab353baf56db77b698d9ef8f","recommendation_url":"https:\/\/myanimelist.net\/recommendations\/anime\/13535-23673","title":"Ookami Shoujo to Kuro Ouji","recommendation_count":1},{"mal_id":18679,"url":"https:\/\/myanimelist.net\/anime\/18679\/Kill_la_Kill","image_url":"https:\/\/cdn.myanimelist.net\/images\/anime\/1464\/111943.jpg?s=b350450d3d98aa57f05bb4fbdb9d5209","recommendation_url":"https:\/\/myanimelist.net\/recommendations\/anime\/13535-18679","title":"Kill la Kill","recommendation_count":1},{"mal_id":1738,"url":"https:\/\/myanimelist.net\/anime\/1738\/Muteki_Kanban_Musume","image_url":"https:\/\/cdn.myanimelist.net\/images\/anime\/7\/26444.jpg?s=6ed7fe672b6ddca9ff386b17288b1d80","recommendation_url":"https:\/\/myanimelist.net\/recommendations\/anime\/1738-13535","title":"Muteki Kanban Musume","recommendation_count":1},{"mal_id":10012,"url":"https:\/\/myanimelist.net\/anime\/10012\/Carnival_Phantasm","image_url":"https:\/\/cdn.myanimelist.net\/images\/anime\/1018\/92921.jpg?s=d1d88b60d5367577c92c08ea60c964da","recommendation_url":"https:\/\/myanimelist.net\/recommendations\/anime\/10012-13535","title":"Carnival Phantasm","recommendation_count":1},{"mal_id":19221,"url":"https:\/\/myanimelist.net\/anime\/19221\/Ore_no_Nounai_Sentakushi_ga_Gakuen_Love_Comedy_wo_Zenryoku_de_Jama_Shiteiru","image_url":"https:\/\/cdn.myanimelist.net\/images\/anime\/10\/53235.jpg?s=f7cf4b4710ac687a8093a9fa048f0509","recommendation_url":"https:\/\/myanimelist.net\/recommendations\/anime\/13535-19221","title":"Ore no Nounai Sentakushi ga, Gakuen Love Comedy wo Zenryoku de Jama Shiteiru","recommendation_count":1},{"mal_id":14713,"url":"https:\/\/myanimelist.net\/anime\/14713\/Kamisama_Hajimemashita","image_url":"https:\/\/cdn.myanimelist.net\/images\/anime\/3\/85429.jpg?s=0edf060bf3cb911d9f3f18fbd976b793","recommendation_url":"https:\/\/myanimelist.net\/recommendations\/anime\/13535-14713","title":"Kamisama Hajimemashita","recommendation_count":1},{"mal_id":7817,"url":"https:\/\/myanimelist.net\/anime\/7817\/B-gata_H-kei","image_url":"https:\/\/cdn.myanimelist.net\/images\/anime\/4\/75227.jpg?s=9f275028ca160d2d9a976e4706eaad61","recommendation_url":"https:\/\/myanimelist.net\/recommendations\/anime\/7817-13535","title":"B-gata H-kei","recommendation_count":1},{"mal_id":32542,"url":"https:\/\/myanimelist.net\/anime\/32542\/Sakamoto_Desu_ga","image_url":"https:\/\/cdn.myanimelist.net\/images\/anime\/4\/79468.jpg?s=7373e097b2fffef594362c7e3466b065","recommendation_url":"https:\/\/myanimelist.net\/recommendations\/anime\/13535-32542","title":"Sakamoto Desu ga?","recommendation_count":1},{"mal_id":383,"url":"https:\/\/myanimelist.net\/anime\/383\/Galaxy_Angel","image_url":"https:\/\/cdn.myanimelist.net\/images\/anime\/4\/6075.jpg?s=8b073e499b27cb4991e7ad683a1374a5","recommendation_url":"https:\/\/myanimelist.net\/recommendations\/anime\/383-13535","title":"Galaxy Angel","recommendation_count":1},{"mal_id":3958,"url":"https:\/\/myanimelist.net\/anime\/3958\/Kannagi","image_url":"https:\/\/cdn.myanimelist.net\/images\/anime\/3\/19724.jpg?s=45210bada370301fcf844803d71933fa","recommendation_url":"https:\/\/myanimelist.net\/recommendations\/anime\/3958-13535","title":"Kannagi","recommendation_count":1},{"mal_id":15109,"url":"https:\/\/myanimelist.net\/anime\/15109\/Cuticle_Tantei_Inaba","image_url":"https:\/\/cdn.myanimelist.net\/images\/anime\/10\/73934.jpg?s=d995f1db0f73fb112ed2792aa356a28e","recommendation_url":"https:\/\/myanimelist.net\/recommendations\/anime\/13535-15109","title":"Cuticle Tantei Inaba","recommendation_count":1},{"mal_id":14765,"url":"https:\/\/myanimelist.net\/anime\/14765\/Ixion_Saga_DT","image_url":"https:\/\/cdn.myanimelist.net\/images\/anime\/8\/42863.jpg?s=5d0b6907b1b4f703c2f8739bce7bcc94","recommendation_url":"https:\/\/myanimelist.net\/recommendations\/anime\/13535-14765","title":"Ixion Saga DT","recommendation_count":1},{"mal_id":8841,"url":"https:\/\/myanimelist.net\/anime\/8841\/Kore_wa_Zombie_Desu_ka","image_url":"https:\/\/cdn.myanimelist.net\/images\/anime\/13\/75521.jpg?s=dc8539c356bf7993c3bd1d0f84241965","recommendation_url":"https:\/\/myanimelist.net\/recommendations\/anime\/8841-13535","title":"Kore wa Zombie Desu ka?","recommendation_count":1},{"mal_id":9934,"url":"https:\/\/myanimelist.net\/anime\/9934\/Nekogami_Yaoyorozu","image_url":"https:\/\/cdn.myanimelist.net\/images\/anime\/2\/73476.jpg?s=1ef8bf24cf029618e7a3aada8b21bf56","recommendation_url":"https:\/\/myanimelist.net\/recommendations\/anime\/9934-13535","title":"Nekogami Yaoyorozu","recommendation_count":1},{"mal_id":23251,"url":"https:\/\/myanimelist.net\/anime\/23251\/Gugure_Kokkuri-san","image_url":"https:\/\/cdn.myanimelist.net\/images\/anime\/6\/65665.jpg?s=aab8e87ffd683b5680a502db45ee350d","recommendation_url":"https:\/\/myanimelist.net\/recommendations\/anime\/13535-23251","title":"Gugure! Kokkuri-san","recommendation_count":1},{"mal_id":32105,"url":"https:\/\/myanimelist.net\/anime\/32105\/Sousei_no_Onmyouji","image_url":"https:\/\/cdn.myanimelist.net\/images\/anime\/12\/79556.jpg?s=df9594d7a0ea4f9173fee5094a378c5a","recommendation_url":"https:\/\/myanimelist.net\/recommendations\/anime\/13535-32105","title":"Sousei no Onmyouji","recommendation_count":1},{"mal_id":11769,"url":"https:\/\/myanimelist.net\/anime\/11769\/Gokujo__Gokurakuin_Joshikou_Ryou_Monogatari","image_url":"https:\/\/cdn.myanimelist.net\/images\/anime\/11\/35659.jpg?s=98a3fdcc3418fe1c48f8792b49258974","recommendation_url":"https:\/\/myanimelist.net\/recommendations\/anime\/11769-13535","title":"Gokujo.: Gokurakuin Joshikou Ryou Monogatari","recommendation_count":1},{"mal_id":253,"url":"https:\/\/myanimelist.net\/anime\/253\/Jungle_wa_Itsumo_Hare_nochi_Guu","image_url":"https:\/\/cdn.myanimelist.net\/images\/anime\/10\/24555.jpg?s=77ce2528f20fb0caf216badd1ed12220","recommendation_url":"https:\/\/myanimelist.net\/recommendations\/anime\/253-13535","title":"Jungle wa Itsumo Hare nochi Guu","recommendation_count":1},{"mal_id":18139,"url":"https:\/\/myanimelist.net\/anime\/18139\/Tonari_no_Seki-kun","image_url":"https:\/\/cdn.myanimelist.net\/images\/anime\/9\/55489.jpg?s=8fc1e99796de3c5f40a8832daba5c89f","recommendation_url":"https:\/\/myanimelist.net\/recommendations\/anime\/13535-18139","title":"Tonari no Seki-kun","recommendation_count":1},{"mal_id":11761,"url":"https:\/\/myanimelist.net\/anime\/11761\/Medaka_Box","image_url":"https:\/\/cdn.myanimelist.net\/images\/anime\/13\/37947.jpg?s=4f944f774288ebf94a383af713eb2591","recommendation_url":"https:\/\/myanimelist.net\/recommendations\/anime\/11761-13535","title":"Medaka Box","recommendation_count":1},{"mal_id":15699,"url":"https:\/\/myanimelist.net\/anime\/15699\/Haiyore_Nyaruko-san_W","image_url":"https:\/\/cdn.myanimelist.net\/images\/anime\/10\/47533.jpg?s=c4c744062a503538dc21b1171018d80f","recommendation_url":"https:\/\/myanimelist.net\/recommendations\/anime\/13535-15699","title":"Haiyore! Nyaruko-san W","recommendation_count":1},{"mal_id":1210,"url":"https:\/\/myanimelist.net\/anime\/1210\/NHK_ni_Youkoso","image_url":"https:\/\/cdn.myanimelist.net\/images\/anime\/3\/52675.jpg?s=e0121ee07b2b86ae6fde9c7f35278a6b","recommendation_url":"https:\/\/myanimelist.net\/recommendations\/anime\/1210-13535","title":"NHK ni Youkoso!","recommendation_count":1},{"mal_id":20457,"url":"https:\/\/myanimelist.net\/anime\/20457\/Inari_Konkon_Koi_Iroha","image_url":"https:\/\/cdn.myanimelist.net\/images\/anime\/8\/64897.jpg?s=7477f95e389a7af19cfc494a891a3922","recommendation_url":"https:\/\/myanimelist.net\/recommendations\/anime\/13535-20457","title":"Inari, Konkon, Koi Iroha.","recommendation_count":1},{"mal_id":14289,"url":"https:\/\/myanimelist.net\/anime\/14289\/Sukitte_Ii_na_yo","image_url":"https:\/\/cdn.myanimelist.net\/images\/anime\/11\/39777.jpg?s=2e1e9b772105988e635fd0f8a18c8248","recommendation_url":"https:\/\/myanimelist.net\/recommendations\/anime\/13535-14289","title":"Sukitte Ii na yo.","recommendation_count":1},{"mal_id":227,"url":"https:\/\/myanimelist.net\/anime\/227\/FLCL","image_url":"https:\/\/cdn.myanimelist.net\/images\/anime\/7\/77356.jpg?s=4c740722edcf938c372197fc31aaa060","recommendation_url":"https:\/\/myanimelist.net\/recommendations\/anime\/227-13535","title":"FLCL","recommendation_count":1},{"mal_id":1500,"url":"https:\/\/myanimelist.net\/anime\/1500\/Teizokurei_Daydream","image_url":"https:\/\/cdn.myanimelist.net\/images\/anime\/8\/3784.jpg?s=4c282cd701875f71c743078bdfa0b792","recommendation_url":"https:\/\/myanimelist.net\/recommendations\/anime\/1500-13535","title":"Teizokurei Daydream","recommendation_count":1},{"mal_id":9969,"url":"https:\/\/myanimelist.net\/anime\/9969\/Gintama","image_url":"https:\/\/cdn.myanimelist.net\/images\/anime\/4\/50361.jpg?s=b3a061db8c3d42a055d58f9df1f3dac7","recommendation_url":"https:\/\/myanimelist.net\/recommendations\/anime\/9969-13535","title":"Gintama'","recommendation_count":1},{"mal_id":50,"url":"https:\/\/myanimelist.net\/anime\/50\/Aa_Megami-sama_TV","image_url":"https:\/\/cdn.myanimelist.net\/images\/anime\/2\/17841.jpg?s=d44799a50db201fab84204e9e1e4c6d8","recommendation_url":"https:\/\/myanimelist.net\/recommendations\/anime\/50-13535","title":"Aa! Megami-sama! (TV)","recommendation_count":1}]}