{"request_hash":"request:anime:ac2647d3c68447fb7d65e895fc25e28b325aaa77","request_cached":false,"request_cache_expiry":86400,"recommendations":[{"mal_id":9213,"url":"https:\/\/myanimelist.net\/anime\/9213\/Kowarekake_no_Orgel","image_url":"https:\/\/cdn.myanimelist.net\/images\/anime\/2\/25552.jpg?s=3641e7f907960bc9e19b8852aa80ad71","recommendation_url":"https:\/\/myanimelist.net\/recommendations\/anime\/2309-9213","title":"Kowarekake no Orgel","recommendation_count":1},{"mal_id":59,"url":"https:\/\/myanimelist.net\/anime\/59\/Chobits","image_url":"https:\/\/cdn.myanimelist.net\/images\/anime\/4\/24648.jpg?s=7f6afcf6ad1aaa44ed50a99e74f32944","recommendation_url":"https:\/\/myanimelist.net\/recommendations\/anime\/59-2309","title":"Chobits","recommendation_count":1},{"mal_id":3167,"url":"https:\/\/myanimelist.net\/anime\/3167\/Eve_no_Jikan","image_url":"https:\/\/cdn.myanimelist.net\/images\/anime\/13\/19480.jpg?s=afbce09f6aae28654b17bfc90e03254f","recommendation_url":"https:\/\/myanimelist.net\/recommendations\/anime\/2309-3167","title":"Eve no Jikan","recommendation_count":1},{"mal_id":276,"url":"https:\/\/myanimelist.net\/anime\/276\/Mahoromatic__Automatic_Maiden","image_url":"https:\/\/cdn.myanimelist.net\/images\/anime\/13\/23051.jpg?s=0a3549672a3d912465924f4436b181dc","recommendation_url":"https:\/\/myanimelist.net\/recommendations\/anime\/276-2309","title":"Mahoromatic: Automatic Maiden","recommendation_count":1},{"mal_id":982,"url":"https:\/\/myanimelist.net\/anime\/982\/Cosplay_Complex","image_url":"https:\/\/cdn.myanimelist.net\/images\/anime\/13\/19185.jpg?s=98e8b997ffbf3ffc4bcb02956ce52ad4","recommendation_url":"https:\/\/myanimelist.net\/recommendations\/anime\/982-2309","title":"Cosplay Complex","recommendation_count":1}]}