{"request_hash":"request:anime:f3591217b1e7592b7c59b04969c13759c285446a","request_cached":false,"request_cache_expiry":86400,"recommendations":[{"mal_id":6586,"url":"https:\/\/myanimelist.net\/anime\/6586\/Yume-iro_P\u00e2tissi\u00e8re","image_url":"https:\/\/cdn.myanimelist.net\/images\/anime\/12\/21674.jpg?s=d5c27e51ab5c22808bd45c4f63229b5f","recommendation_url":"https:\/\/myanimelist.net\/recommendations\/anime\/6586-25839","title":"Yume-iro P\u00e2tissi\u00e8re","recommendation_count":7},{"mal_id":10321,"url":"https:\/\/myanimelist.net\/anime\/10321\/Uta_no\u2606Prince-sama\u266a__Maji_Love_1000","image_url":"https:\/\/cdn.myanimelist.net\/images\/anime\/6\/30248.jpg?s=6177c34a2632d34708e9cc50470838bc","recommendation_url":"https:\/\/myanimelist.net\/recommendations\/anime\/10321-25839","title":"Uta no\u2606Prince-sama\u266a: Maji Love 1000%","recommendation_count":2},{"mal_id":33447,"url":"https:\/\/myanimelist.net\/anime\/33447\/Piace__Watashi_no_Italian","image_url":"https:\/\/cdn.myanimelist.net\/images\/anime\/8\/83098.jpg?s=a3676611c37d2836c4d02390975051dd","recommendation_url":"https:\/\/myanimelist.net\/recommendations\/anime\/25839-33447","title":"Piace: Watashi no Italian","recommendation_count":1},{"mal_id":28171,"url":"https:\/\/myanimelist.net\/anime\/28171\/Shokugeki_no_Souma","image_url":"https:\/\/cdn.myanimelist.net\/images\/anime\/3\/72943.jpg?s=a93f0e87eb1a78ff9dd281cfbb236bbf","recommendation_url":"https:\/\/myanimelist.net\/recommendations\/anime\/25839-28171","title":"Shokugeki no Souma","recommendation_count":1},{"mal_id":27727,"url":"https:\/\/myanimelist.net\/anime\/27727\/Binan_Koukou_Chikyuu_Boueibu_LOVE","image_url":"https:\/\/cdn.myanimelist.net\/images\/anime\/10\/68451.jpg?s=fd3c92ce65abd0ae21c012d339efcff2","recommendation_url":"https:\/\/myanimelist.net\/recommendations\/anime\/25839-27727","title":"Binan Koukou Chikyuu Boueibu LOVE!","recommendation_count":1},{"mal_id":19841,"url":"https:\/\/myanimelist.net\/anime\/19841\/Super_Seisyun_Brothers","image_url":"https:\/\/cdn.myanimelist.net\/images\/anime\/2\/53807.jpg?s=564a3a59d3902ff7cc0adc0f6dd3a55a","recommendation_url":"https:\/\/myanimelist.net\/recommendations\/anime\/19841-25839","title":"Super Seisyun Brothers","recommendation_count":1},{"mal_id":34393,"url":"https:\/\/myanimelist.net\/anime\/34393\/Room_Mate","image_url":"https:\/\/cdn.myanimelist.net\/images\/anime\/10\/85196.jpg?s=998eefdd484d986a0e0639f8c1c0371e","recommendation_url":"https:\/\/myanimelist.net\/recommendations\/anime\/25839-34393","title":"Room Mate","recommendation_count":1},{"mal_id":33299,"url":"https:\/\/myanimelist.net\/anime\/33299\/Magic-Kyun_Renaissance","image_url":"https:\/\/cdn.myanimelist.net\/images\/anime\/7\/80828.jpg?s=6995cf7d99d9cb603f3291b003ae3c4c","recommendation_url":"https:\/\/myanimelist.net\/recommendations\/anime\/25839-33299","title":"Magic-Kyun! Renaissance","recommendation_count":1},{"mal_id":15605,"url":"https:\/\/myanimelist.net\/anime\/15605\/Brothers_Conflict","image_url":"https:\/\/cdn.myanimelist.net\/images\/anime\/5\/51409.jpg?s=91c4aa80788be2c18eb7c43d1ba854a2","recommendation_url":"https:\/\/myanimelist.net\/recommendations\/anime\/15605-25839","title":"Brothers Conflict","recommendation_count":1},{"mal_id":13833,"url":"https:\/\/myanimelist.net\/anime\/13833\/Nagareboshi_Lens","image_url":"https:\/\/cdn.myanimelist.net\/images\/anime\/7\/38377.jpg?s=a34df2d9d4e1729afcb94301fa097d2f","recommendation_url":"https:\/\/myanimelist.net\/recommendations\/anime\/13833-25839","title":"Nagareboshi Lens","recommendation_count":1},{"mal_id":7705,"url":"https:\/\/myanimelist.net\/anime\/7705\/Starry\u2606Sky","image_url":"https:\/\/cdn.myanimelist.net\/images\/anime\/7\/27459.jpg?s=92268ad1d504d7e19e5e3e06ca4f8534","recommendation_url":"https:\/\/myanimelist.net\/recommendations\/anime\/7705-25839","title":"Starry\u2606Sky","recommendation_count":1},{"mal_id":7103,"url":"https:\/\/myanimelist.net\/anime\/7103\/Miracle\u2606Train__Oedo-sen_e_Youkoso","image_url":"https:\/\/cdn.myanimelist.net\/images\/anime\/9\/75568.jpg?s=3373a288802997f6bc63f846df786fea","recommendation_url":"https:\/\/myanimelist.net\/recommendations\/anime\/7103-25839","title":"Miracle\u2606Train: Oedo-sen e Youkoso","recommendation_count":1},{"mal_id":853,"url":"https:\/\/myanimelist.net\/anime\/853\/Ouran_Koukou_Host_Club","image_url":"https:\/\/cdn.myanimelist.net\/images\/anime\/2\/71992.jpg?s=83447b9f62a31c405dd9cdb456fa394e","recommendation_url":"https:\/\/myanimelist.net\/recommendations\/anime\/853-25839","title":"Ouran Koukou Host Club","recommendation_count":1},{"mal_id":17513,"url":"https:\/\/myanimelist.net\/anime\/17513\/Diabolik_Lovers","image_url":"https:\/\/cdn.myanimelist.net\/images\/anime\/9\/51989.jpg?s=86f70316a29611d52021f41a37edf6fd","recommendation_url":"https:\/\/myanimelist.net\/recommendations\/anime\/17513-25839","title":"Diabolik Lovers","recommendation_count":1},{"mal_id":28,"url":"https:\/\/myanimelist.net\/anime\/28\/Yakitate_Japan","image_url":"https:\/\/cdn.myanimelist.net\/images\/anime\/3\/76432.jpg?s=b386933474776a795405439f742b0d11","recommendation_url":"https:\/\/myanimelist.net\/recommendations\/anime\/28-25839","title":"Yakitate!! Japan","recommendation_count":1},{"mal_id":14145,"url":"https:\/\/myanimelist.net\/anime\/14145\/Hanayaka_Nari_Waga_Ichizoku__Kinetograph","image_url":"https:\/\/cdn.myanimelist.net\/images\/anime\/2\/45356.jpg?s=e5203be0ddb41346ac18d4123a60bc29","recommendation_url":"https:\/\/myanimelist.net\/recommendations\/anime\/14145-25839","title":"Hanayaka Nari, Waga Ichizoku: Kinetograph","recommendation_count":1}]}