{"request_hash":"request:anime:36f09dba13de81b9f6969e584b762f12bd2c8a8d","request_cached":false,"request_cache_expiry":86400,"recommendations":[{"mal_id":15051,"url":"https:\/\/myanimelist.net\/anime\/15051\/Love_Live_School_Idol_Project","image_url":"https:\/\/cdn.myanimelist.net\/images\/anime\/11\/56849.jpg?s=125be45b8c0140f6d752891a69b4f517","recommendation_url":"https:\/\/myanimelist.net\/recommendations\/anime\/15051-34257","title":"Love Live! School Idol Project","recommendation_count":1},{"mal_id":38835,"url":"https:\/\/myanimelist.net\/anime\/38835\/Umayon","image_url":"https:\/\/cdn.myanimelist.net\/images\/anime\/1032\/111641.jpg?s=decd25d015fcc5267e717a654ec3b01a","recommendation_url":"https:\/\/myanimelist.net\/recommendations\/anime\/34257-38835","title":"Umayon","recommendation_count":1}]}