{"request_hash":"request:anime:365602fc2e66f68ed21bbbe02d80946b5aca626b","request_cached":false,"request_cache_expiry":86400,"recommendations":[{"mal_id":3702,"url":"https:\/\/myanimelist.net\/anime\/3702\/Detroit_Metal_City","image_url":"https:\/\/cdn.myanimelist.net\/images\/anime\/3\/9853.jpg?s=01409a7f61f078eb0661eced9e766389","recommendation_url":"https:\/\/myanimelist.net\/recommendations\/anime\/3702-36904","title":"Detroit Metal City","recommendation_count":3},{"mal_id":46102,"url":"https:\/\/myanimelist.net\/anime\/46102\/Odd_Taxi","image_url":"https:\/\/cdn.myanimelist.net\/images\/anime\/1981\/113348.jpg?s=38082dbb5a64de5fc2129a59c46c3fe0","recommendation_url":"https:\/\/myanimelist.net\/recommendations\/anime\/36904-46102","title":"Odd Taxi","recommendation_count":3},{"mal_id":36317,"url":"https:\/\/myanimelist.net\/anime\/36317\/Gaikotsu_Shotenin_Honda-san","image_url":"https:\/\/cdn.myanimelist.net\/images\/anime\/1555\/93865.jpg?s=6c8b8f5f46c39d9c6d3313ce986ade6d","recommendation_url":"https:\/\/myanimelist.net\/recommendations\/anime\/36317-36904","title":"Gaikotsu Shotenin Honda-san","recommendation_count":2},{"mal_id":40620,"url":"https:\/\/myanimelist.net\/anime\/40620\/Uramichi_Oniisan","image_url":"https:\/\/cdn.myanimelist.net\/images\/anime\/1126\/115635.jpg?s=d1bc5fe7cf2facbaf324f5853182ba1e","recommendation_url":"https:\/\/myanimelist.net\/recommendations\/anime\/36904-40620","title":"Uramichi Oniisan","recommendation_count":2},{"mal_id":33255,"url":"https:\/\/myanimelist.net\/anime\/33255\/Saiki_Kusuo_no_\u03a8-nan","image_url":"https:\/\/cdn.myanimelist.net\/images\/anime\/11\/80167.jpg?s=1c4f87499deea4f4dbc09805e23bf243","recommendation_url":"https:\/\/myanimelist.net\/recommendations\/anime\/33255-36904","title":"Saiki Kusuo no \u03a8-nan","recommendation_count":2},{"mal_id":39195,"url":"https:\/\/myanimelist.net\/anime\/39195\/Beastars","image_url":"https:\/\/cdn.myanimelist.net\/images\/anime\/1234\/102008.jpg?s=cda3b8258f2358733b570b673612bfdb","recommendation_url":"https:\/\/myanimelist.net\/recommendations\/anime\/36904-39195","title":"Beastars","recommendation_count":2},{"mal_id":35968,"url":"https:\/\/myanimelist.net\/anime\/35968\/Wotaku_ni_Koi_wa_Muzukashii","image_url":"https:\/\/cdn.myanimelist.net\/images\/anime\/1864\/93518.jpg?s=b05fb47d89f6b9ae039a5bce238f630a","recommendation_url":"https:\/\/myanimelist.net\/recommendations\/anime\/35968-36904","title":"Wotaku ni Koi wa Muzukashii","recommendation_count":2},{"mal_id":35777,"url":"https:\/\/myanimelist.net\/anime\/35777\/Rilakkuma_to_Kaoru-san","image_url":"https:\/\/cdn.myanimelist.net\/images\/anime\/1582\/100702.jpg?s=82f3493be9043a29dc17ee95bf1f1dd0","recommendation_url":"https:\/\/myanimelist.net\/recommendations\/anime\/35777-36904","title":"Rilakkuma to Kaoru-san","recommendation_count":2},{"mal_id":39849,"url":"https:\/\/myanimelist.net\/anime\/39849\/Kyouryuu_Shoujo_Gauko","image_url":"https:\/\/cdn.myanimelist.net\/images\/anime\/1158\/101098.jpg?s=c643bcc4757bef6b861ec3dc0946369f","recommendation_url":"https:\/\/myanimelist.net\/recommendations\/anime\/36904-39849","title":"Kyouryuu Shoujo Gauko","recommendation_count":2},{"mal_id":37920,"url":"https:\/\/myanimelist.net\/anime\/37920\/Ueno-san_wa_Bukiyou","image_url":"https:\/\/cdn.myanimelist.net\/images\/anime\/1874\/111374.jpg?s=383c9eb2a83f5fc54689314ca6abe423","recommendation_url":"https:\/\/myanimelist.net\/recommendations\/anime\/36904-37920","title":"Ueno-san wa Bukiyou","recommendation_count":1},{"mal_id":7785,"url":"https:\/\/myanimelist.net\/anime\/7785\/Yojouhan_Shinwa_Taikei","image_url":"https:\/\/cdn.myanimelist.net\/images\/anime\/10\/50457.jpg?s=e159597465fa4799df1f8128a8683750","recommendation_url":"https:\/\/myanimelist.net\/recommendations\/anime\/7785-36904","title":"Yojouhan Shinwa Taikei","recommendation_count":1},{"mal_id":27757,"url":"https:\/\/myanimelist.net\/anime\/27757\/Anisava","image_url":"https:\/\/cdn.myanimelist.net\/images\/anime\/12\/67189.jpg?s=911dfdb4983676e4f0eb539e9b2ad82c","recommendation_url":"https:\/\/myanimelist.net\/recommendations\/anime\/27757-36904","title":"Anisava","recommendation_count":1},{"mal_id":43001,"url":"https:\/\/myanimelist.net\/anime\/43001\/Youjo_Shachou","image_url":"https:\/\/cdn.myanimelist.net\/images\/anime\/1844\/110500.jpg?s=3d1f8306cd912d089cf4d901cb7c6395","recommendation_url":"https:\/\/myanimelist.net\/recommendations\/anime\/36904-43001","title":"Youjo Shachou","recommendation_count":1},{"mal_id":2236,"url":"https:\/\/myanimelist.net\/anime\/2236\/Toki_wo_Kakeru_Shoujo","image_url":"https:\/\/cdn.myanimelist.net\/images\/anime\/1\/2432.jpg?s=6c3f5019a71d693be414555453678898","recommendation_url":"https:\/\/myanimelist.net\/recommendations\/anime\/2236-36904","title":"Toki wo Kakeru Shoujo","recommendation_count":1},{"mal_id":6956,"url":"https:\/\/myanimelist.net\/anime\/6956\/Working","image_url":"https:\/\/cdn.myanimelist.net\/images\/anime\/10\/75262.jpg?s=6077f0616e8fab853db4a3039b86c457","recommendation_url":"https:\/\/myanimelist.net\/recommendations\/anime\/6956-36904","title":"Working!!","recommendation_count":1},{"mal_id":18119,"url":"https:\/\/myanimelist.net\/anime\/18119\/Servant_x_Service","image_url":"https:\/\/cdn.myanimelist.net\/images\/anime\/13\/51579.jpg?s=42fb6e82aa30c7d7478038b741882a8c","recommendation_url":"https:\/\/myanimelist.net\/recommendations\/anime\/18119-36904","title":"Servant x Service","recommendation_count":1},{"mal_id":36873,"url":"https:\/\/myanimelist.net\/anime\/36873\/Back_Street_Girls__Gokudolls","image_url":"https:\/\/cdn.myanimelist.net\/images\/anime\/1484\/93140.jpg?s=6a9efd54248b3f839dafeae0f57fea5b","recommendation_url":"https:\/\/myanimelist.net\/recommendations\/anime\/36873-36904","title":"Back Street Girls: Gokudolls","recommendation_count":1},{"mal_id":39590,"url":"https:\/\/myanimelist.net\/anime\/39590\/Africa_no_Salaryman_TV","image_url":"https:\/\/cdn.myanimelist.net\/images\/anime\/1937\/102309.jpg?s=a38fa5563e1164024958320603ba7f57","recommendation_url":"https:\/\/myanimelist.net\/recommendations\/anime\/36904-39590","title":"Africa no Salaryman (TV)","recommendation_count":1},{"mal_id":16149,"url":"https:\/\/myanimelist.net\/anime\/16149\/Kick-Heart","image_url":"https:\/\/cdn.myanimelist.net\/images\/anime\/3\/46509.jpg?s=731b7c3194cc03d39f1dd6c6c775ee0c","recommendation_url":"https:\/\/myanimelist.net\/recommendations\/anime\/16149-36904","title":"Kick-Heart","recommendation_count":1},{"mal_id":35015,"url":"https:\/\/myanimelist.net\/anime\/35015\/Ani_ni_Tsukeru_Kusuri_wa_Nai","image_url":"https:\/\/cdn.myanimelist.net\/images\/anime\/4\/85295.jpg?s=e551133221a2dfef9ceacbc76066477c","recommendation_url":"https:\/\/myanimelist.net\/recommendations\/anime\/35015-36904","title":"Ani ni Tsukeru Kusuri wa Nai!","recommendation_count":1}]}