{"request_hash":"request:anime:d7a2a0b1e994b2724b3aeb5e36df827f261bb8ba","request_cached":false,"request_cache_expiry":86400,"recommendations":[{"mal_id":66,"url":"https:\/\/myanimelist.net\/anime\/66\/Azumanga_Daioh","image_url":"https:\/\/cdn.myanimelist.net\/images\/anime\/1\/66.jpg?s=3ab1985c4a76949c97adbd847ef0c209","recommendation_url":"https:\/\/myanimelist.net\/recommendations\/anime\/66-9074","title":"Azumanga Daioh","recommendation_count":1},{"mal_id":227,"url":"https:\/\/myanimelist.net\/anime\/227\/FLCL","image_url":"https:\/\/cdn.myanimelist.net\/images\/anime\/7\/77356.jpg?s=4c740722edcf938c372197fc31aaa060","recommendation_url":"https:\/\/myanimelist.net\/recommendations\/anime\/227-9074","title":"FLCL","recommendation_count":1},{"mal_id":918,"url":"https:\/\/myanimelist.net\/anime\/918\/Gintama","image_url":"https:\/\/cdn.myanimelist.net\/images\/anime\/10\/73274.jpg?s=ed42453c10ba12b03b1600d02725a174","recommendation_url":"https:\/\/myanimelist.net\/recommendations\/anime\/918-9074","title":"Gintama","recommendation_count":1},{"mal_id":4477,"url":"https:\/\/myanimelist.net\/anime\/4477\/Nodame_Cantabile__Paris-hen","image_url":"https:\/\/cdn.myanimelist.net\/images\/anime\/4\/11918.jpg?s=cab2acd88a6b535646895d7224eac860","recommendation_url":"https:\/\/myanimelist.net\/recommendations\/anime\/4477-9074","title":"Nodame Cantabile: Paris-hen","recommendation_count":1},{"mal_id":1210,"url":"https:\/\/myanimelist.net\/anime\/1210\/NHK_ni_Youkoso","image_url":"https:\/\/cdn.myanimelist.net\/images\/anime\/3\/52675.jpg?s=e0121ee07b2b86ae6fde9c7f35278a6b","recommendation_url":"https:\/\/myanimelist.net\/recommendations\/anime\/1210-9074","title":"NHK ni Youkoso!","recommendation_count":1},{"mal_id":2605,"url":"https:\/\/myanimelist.net\/anime\/2605\/Sayonara_Zetsubou_Sensei","image_url":"https:\/\/cdn.myanimelist.net\/images\/anime\/5\/6559.jpg?s=1fa13ba08de3616a0913c6d847572f10","recommendation_url":"https:\/\/myanimelist.net\/recommendations\/anime\/2605-9074","title":"Sayonara Zetsubou Sensei","recommendation_count":1},{"mal_id":5081,"url":"https:\/\/myanimelist.net\/anime\/5081\/Bakemonogatari","image_url":"https:\/\/cdn.myanimelist.net\/images\/anime\/11\/75274.jpg?s=3bb5c42c0803621dde09c52f5c4d4249","recommendation_url":"https:\/\/myanimelist.net\/recommendations\/anime\/5081-9074","title":"Bakemonogatari","recommendation_count":1}]}