{"request_hash":"request:anime:8c95fb30f66ecc53adbc32ac07a38347f495986c","request_cached":false,"request_cache_expiry":86400,"mal_id":32419,"url":"https:\/\/myanimelist.net\/anime\/32419\/Chibinacs_3","image_url":"https:\/\/cdn.myanimelist.net\/images\/anime\/11\/77794.jpg","trailer_url":null,"title":"Chibinacs 3","title_english":null,"title_japanese":"\u30c1\u30d3\u30ca\u30c3\u30af\u30b93","title_synonyms":["Chibinacs\u00b3"],"type":"TV","source":"Other","episodes":25,"status":"Finished Airing","airing":false,"aired":{"from":"2008-06-03T00:00:00+00:00","to":"2008-11-18T00:00:00+00:00","prop":{"from":{"day":3,"month":6,"year":2008},"to":{"day":18,"month":11,"year":2008}},"string":"Jun 3, 2008 to Nov 18, 2008"},"duration":"3 min per ep","rating":"G - All Ages","score":null,"scored_by":null,"rank":14959,"popularity":16316,"members":176,"favorites":0,"synopsis":"The 3rd and final season of Chibinacs.","background":null,"premiered":"Summer 2008","broadcast":"Tuesdays at 00:49 (JST)","related":{"Prequel":[{"mal_id":32418,"type":"anime","name":"Chibinacs 2.0","url":"https:\/\/myanimelist.net\/anime\/32418\/Chibinacs_20"}]},"producers":[],"licensors":[],"studios":[],"genres":[{"mal_id":4,"type":"anime","name":"Comedy","url":"https:\/\/myanimelist.net\/anime\/genre\/4\/Comedy"}],"explicit_genres":[],"demographics":[],"themes":[],"opening_themes":[],"ending_themes":[],"external_links":[{"name":"Official Site","url":"http:\/\/web.archive.org\/web\/20100604030130\/http:\/\/www.stv.ne.jp\/tv\/chibinacs\/index.html"},{"name":"Wikipedia","url":"https:\/\/ja.wikipedia.org\/wiki\/%E3%83%81%E3%83%93%E3%83%8A%E3%83%83%E3%82%AF%E3%82%B9"}]}