{"request_hash":"request:anime:c9c33c77e1f81e0190a12fafe8017235287675d5","request_cached":false,"request_cache_expiry":86400,"mal_id":34436,"url":"https:\/\/myanimelist.net\/anime\/34436\/Age_of_Obscure__Boubaku_Jidai","image_url":"https:\/\/cdn.myanimelist.net\/images\/anime\/1526\/90848.jpg","trailer_url":null,"title":"Age of Obscure: Boubaku Jidai","title_english":null,"title_japanese":"AGE OF OBSCURE \u832b\u6f20\u6642\u4ee3","title_synonyms":[],"type":"Movie","source":"Original","episodes":1,"status":"Finished Airing","airing":false,"aired":{"from":"2016-01-01T00:00:00+00:00","to":null,"prop":{"from":{"day":1,"month":1,"year":2016},"to":{"day":null,"month":null,"year":null}},"string":"2016"},"duration":"4 min","rating":"G - All Ages","score":null,"scored_by":null,"rank":14506,"popularity":14246,"members":318,"favorites":0,"synopsis":"Short film by Mirai Mizue and Onohana with music by Twoth.","background":null,"premiered":null,"broadcast":null,"related":{},"producers":[],"licensors":[],"studios":[],"genres":[{"mal_id":5,"type":"anime","name":"Avant Garde","url":"https:\/\/myanimelist.net\/anime\/genre\/5\/Avant_Garde"}],"explicit_genres":[],"demographics":[],"themes":[],"opening_themes":[],"ending_themes":[],"external_links":[{"name":"AnimeDB","url":"http:\/\/anidb.info\/perl-bin\/animedb.pl?show=anime&aid=13930"}]}