{"request_hash":"request:anime:a51a846420daca837fc39d61385ece463d98c367","request_cached":false,"request_cache_expiry":86400,"mal_id":40960,"url":"https:\/\/myanimelist.net\/anime\/40960\/Cheat_Kusushi_no_Slow_Life__Isekai_ni_Tsukurou_Drugstore","image_url":"https:\/\/cdn.myanimelist.net\/images\/anime\/1787\/115817.jpg","trailer_url":"https:\/\/www.youtube.com\/embed\/VTXeHBjq-AI?enablejsapi=1&wmode=opaque&autoplay=1","title":"Cheat Kusushi no Slow Life: Isekai ni Tsukurou Drugstore","title_english":null,"title_japanese":"\u30c1\u30fc\u30c8\u85ac\u5e2b\u306e\u30b9\u30ed\u30fc\u30e9\u30a4\u30d5\uff5e\u7570\u4e16\u754c\u306b\u4f5c\u308d\u3046\u30c9\u30e9\u30c3\u30b0\u30b9\u30c8\u30a2\uff5e","title_synonyms":["Cheat Pharmacist's Slow Life: Making a Drugstore in Another World"],"type":"TV","source":"Light novel","episodes":12,"status":"Finished Airing","airing":false,"aired":{"from":"2021-07-07T00:00:00+00:00","to":"2021-09-22T00:00:00+00:00","prop":{"from":{"day":7,"month":7,"year":2021},"to":{"day":22,"month":9,"year":2021}},"string":"Jul 7, 2021 to Sep 22, 2021"},"duration":"23 min per ep","rating":"PG-13 - Teens 13 or older","score":6.52,"scored_by":19199,"rank":5983,"popularity":1852,"members":81182,"favorites":483,"synopsis":"Reiji Kirio, formerly a corporate slave, wakes up one day in another world. After discovering that he has gained superhuman pharmaceutical knowledge, he decides to open up a drugstore alongside the canine Noera and the ghostly Mina. There, he tends to the needs of all who visit the shop with potions and the like. Cheat Kusushi no Slow Life: Isekai ni Tsukurou Drugstore follows the slow but often hectic days of Reiji's drugstore. [Written by MAL Rewrite]","background":"Cheat Kusushi no Slow Life: Isekai ni Tsukurou Drugstore was first announced at Comiket 97 on December 28, 2019.","premiered":"Summer 2021","broadcast":"Wednesdays at 22:00 (JST)","related":{"Adaptation":[{"mal_id":103995,"type":"manga","name":"Cheat Kusushi no Slow Life: Isekai ni Tsukurou Drugstore","url":"https:\/\/myanimelist.net\/manga\/103995\/Cheat_Kusushi_no_Slow_Life__Isekai_ni_Tsukurou_Drugstore"}]},"producers":[],"licensors":[],"studios":[{"mal_id":1264,"type":"anime","name":"EMT Squared","url":"https:\/\/myanimelist.net\/anime\/producer\/1264\/EMT_Squared"}],"genres":[{"mal_id":4,"type":"anime","name":"Comedy","url":"https:\/\/myanimelist.net\/anime\/genre\/4\/Comedy"},{"mal_id":10,"type":"anime","name":"Fantasy","url":"https:\/\/myanimelist.net\/anime\/genre\/10\/Fantasy"}],"explicit_genres":[],"demographics":[],"themes":[],"opening_themes":[],"ending_themes":[],"external_links":[{"name":"Official Site","url":"http:\/\/www.cheat-kusushi.jp\/"},{"name":"AnimeDB","url":"http:\/\/anidb.info\/perl-bin\/animedb.pl?show=anime&aid=15339"},{"name":"AnimeNewsNetwork","url":"http:\/\/www.animenewsnetwork.com\/encyclopedia\/anime.php?id=23901"},{"name":"Wikipedia","url":"https:\/\/en.wikipedia.org\/wiki\/Cheat_Kusushi_no_Slow_Life:_Isekai_ni_Tsukur%C5%8D_Drugstore"}]}