{"request_hash":"request:anime:efa6ae2cfe29458608ab9b7cfd15f9a02e235ec9","request_cached":true,"request_cache_expiry":57835,"mal_id":43329,"url":"https:\/\/myanimelist.net\/anime\/43329\/Da_Nao_Hua_Shi","image_url":"https:\/\/cdn.myanimelist.net\/img\/sp\/icon\/apple-touch-icon-256.png","trailer_url":null,"title":"Da Nao Hua Shi","title_english":null,"title_japanese":"\u5927\u9b27\u756b\u5ba4","title_synonyms":["Uproar in the Studio","Studio Scene"],"type":"Movie","source":"Original","episodes":1,"status":"Finished Airing","airing":false,"aired":{"from":"1927-05-01T00:00:00+00:00","to":null,"prop":{"from":{"day":1,"month":5,"year":1927},"to":{"day":null,"month":null,"year":null}},"string":"May 1927"},"duration":"10 min","rating":"G - All Ages","score":null,"scored_by":null,"rank":15098,"popularity":18734,"members":9,"favorites":0,"synopsis":null,"background":null,"premiered":null,"broadcast":null,"related":{},"producers":[],"licensors":[],"studios":[],"genres":[{"mal_id":4,"type":"anime","name":"Comedy","url":"https:\/\/myanimelist.net\/anime\/genre\/4\/Comedy"}],"explicit_genres":[],"demographics":[],"themes":[],"opening_themes":["No opening themes have been added to this title. Help improve our database by adding an opening theme here."],"ending_themes":["No ending themes have been added to this title. Help improve our database by adding an ending theme here."],"external_links":[{"name":"Official Site","url":"https:\/\/movie.douban.com\/subject\/2348527\/"},{"name":"Wikipedia","url":"https:\/\/zh.wikipedia.org\/wiki\/%E5%A4%A7%E9%97%B9%E7%94%BB%E5%AE%A4"}]}