{"request_hash":"request:anime:60aa5670d2e42b52fc4fdbbc41c072f7b1da349d","request_cached":false,"request_cache_expiry":86400,"mal_id":48225,"url":"https:\/\/myanimelist.net\/anime\/48225\/Buluwa_Supsog_Chingudeul","image_url":"https:\/\/cdn.myanimelist.net\/img\/sp\/icon\/apple-touch-icon-256.png","trailer_url":null,"title":"Buluwa Supsog Chingudeul","title_english":null,"title_japanese":"\ubd80\ub8e8\uc640 \uc232\uc18d \uce5c\uad6c\ub4e4","title_synonyms":[],"type":"TV","source":"Original","episodes":26,"status":"Finished Airing","airing":false,"aired":{"from":null,"to":null,"prop":{"from":{"day":null,"month":null,"year":null},"to":{"day":null,"month":null,"year":null}},"string":"Not available"},"duration":"22 min per ep","rating":"PG - Children","score":null,"scored_by":null,"rank":0,"popularity":0,"members":0,"favorites":0,"synopsis":null,"background":null,"premiered":null,"broadcast":"Unknown","related":{},"producers":[],"licensors":[],"studios":[],"genres":[{"mal_id":10,"type":"anime","name":"Fantasy","url":"https:\/\/myanimelist.net\/anime\/genre\/10\/Fantasy"}],"explicit_genres":[],"demographics":[],"themes":[],"opening_themes":[],"ending_themes":[],"external_links":[]}