{"request_hash":"request:anime:3ecb697ba8e84dc24076c0ee595547c76d8bf948","request_cached":false,"request_cache_expiry":86400,"mal_id":48276,"url":"https:\/\/myanimelist.net\/anime\/48276\/Appa_eolil_Jeog-en","image_url":"https:\/\/cdn.myanimelist.net\/images\/anime\/1444\/115555.jpg","trailer_url":null,"title":"Appa eolil Jeog-en","title_english":null,"title_japanese":"\uc544\ube60 \uc5b4\ub9b4 \uc801\uc5d4","title_synonyms":[],"type":"TV","source":"Unknown","episodes":26,"status":"Finished Airing","airing":false,"aired":{"from":"2016-01-12T00:00:00+00:00","to":"2016-07-26T00:00:00+00:00","prop":{"from":{"day":12,"month":1,"year":2016},"to":{"day":26,"month":7,"year":2016}},"string":"Jan 12, 2016 to Jul 26, 2016"},"duration":"22 min per ep","rating":"PG - Children","score":null,"scored_by":null,"rank":14608,"popularity":18262,"members":33,"favorites":0,"synopsis":null,"background":null,"premiered":"Winter 2016","broadcast":"Unknown","related":{},"producers":[],"licensors":[],"studios":[],"genres":[],"explicit_genres":[],"demographics":[{"mal_id":15,"type":"anime","name":"Kids","url":"https:\/\/myanimelist.net\/anime\/genre\/15\/Kids"}],"themes":[],"opening_themes":[],"ending_themes":[],"external_links":[{"name":"Official Site","url":"https:\/\/www.youtube.com\/playlist?list=PLX5EBLrGssw5TdlsjuwjGiugfellJDjzb"},{"name":"Wikipedia","url":"https:\/\/ko.wikipedia.org\/wiki\/%EC%95%84%EB%B9%A0_%EC%96%B4%EB%A6%B4_%EC%A0%81%EC%97%94"}]}