{"request_hash":"request:anime:b0102c5c61f6eb9af5bf8a01a5ec641a77f5add4","request_cached":false,"request_cache_expiry":86400,"mal_id":48877,"url":"https:\/\/myanimelist.net\/anime\/48877\/5-fun_de_Wakaru_Kingdom__Gasshougun-hen","image_url":"https:\/\/cdn.myanimelist.net\/images\/anime\/1546\/115588.jpg","trailer_url":null,"title":"5-fun de Wakaru! Kingdom: Gasshougun-hen","title_english":null,"title_japanese":"5\u5206\u3067\u308f\u304b\u308b\uff01TV\u30a2\u30cb\u30e1\u300c\u30ad\u30f3\u30b0\u30c0\u30e0\u300d\u5408\u5f93\u8ecd\u7de8","title_synonyms":["Kingdom Season 3 Recap in 5 Minutes"],"type":"ONA","source":"Manga","episodes":2,"status":"Finished Airing","airing":false,"aired":{"from":"2020-04-02T00:00:00+00:00","to":"2021-03-28T00:00:00+00:00","prop":{"from":{"day":2,"month":4,"year":2020},"to":{"day":28,"month":3,"year":2021}},"string":"Apr 2, 2020 to Mar 28, 2021"},"duration":"5 min per ep","rating":"PG-13 - Teens 13 or older","score":null,"scored_by":null,"rank":14484,"popularity":15910,"members":206,"favorites":0,"synopsis":null,"background":null,"premiered":null,"broadcast":null,"related":{"Full story":[{"mal_id":40682,"type":"anime","name":"Kingdom 3rd Season","url":"https:\/\/myanimelist.net\/anime\/40682\/Kingdom_3rd_Season"}]},"producers":[],"licensors":[],"studios":[{"mal_id":1998,"type":"anime","name":"Studio Signpost","url":"https:\/\/myanimelist.net\/anime\/producer\/1998\/Studio_Signpost"}],"genres":[{"mal_id":1,"type":"anime","name":"Action","url":"https:\/\/myanimelist.net\/anime\/genre\/1\/Action"}],"explicit_genres":[],"demographics":[{"mal_id":42,"type":"anime","name":"Seinen","url":"https:\/\/myanimelist.net\/anime\/genre\/42\/Seinen"}],"themes":[{"mal_id":13,"type":"anime","name":"Historical","url":"https:\/\/myanimelist.net\/anime\/genre\/13\/Historical"},{"mal_id":38,"type":"anime","name":"Military","url":"https:\/\/myanimelist.net\/anime\/genre\/38\/Military"}],"opening_themes":[],"ending_themes":[],"external_links":[{"name":"Official Site","url":"https:\/\/kingdom-anime.com\/\u200b"}]}